README.md
disorder.py
setup.cfg
setup.py
nosedisorder/__init__.py
nosedisorder/disorder.py
nosedisorder.egg-info/PKG-INFO
nosedisorder.egg-info/SOURCES.txt
nosedisorder.egg-info/dependency_links.txt
nosedisorder.egg-info/entry_points.txt
nosedisorder.egg-info/top_level.txt